etc/odcs/config.py
etc/odcs/pungi.conf
etc/odcs/raw_config_wrapper.conf
odcs/__init__.py
odcs/__init__.pyc
odcs/__pycache__/__init__.cpython-36.pyc
odcs/__pycache__/__init__.cpython-37.pyc
odcs/__pycache__/__init__.cpython-38.pyc
odcs/client/__init__.py
odcs/client/__init__.pyc
odcs/client/odcs.py
odcs/client/odcs.pyc
odcs/client/__pycache__/__init__.cpython-36.pyc
odcs/client/__pycache__/__init__.cpython-37.pyc
odcs/client/__pycache__/__init__.cpython-38.pyc
odcs/client/__pycache__/odcs.cpython-36.pyc
odcs/client/__pycache__/odcs.cpython-37.pyc
odcs/client/__pycache__/odcs.cpython-38.pyc
odcs/common/__init__.py
odcs/common/__init__.pyc
odcs/common/types.py
odcs/common/types.pyc
odcs/common/__pycache__/__init__.cpython-36.pyc
odcs/common/__pycache__/__init__.cpython-37.pyc
odcs/common/__pycache__/__init__.cpython-38.pyc
odcs/common/__pycache__/types.cpython-36.pyc
odcs/common/__pycache__/types.cpython-37.pyc
odcs/common/__pycache__/types.cpython-38.pyc
odcs/server/.auth.py.swp
odcs/server/.errors.py.swp
odcs/server/.events.py.swp
odcs/server/.views.py.swp
odcs/server/__init__.py
odcs/server/__init__.pyc
odcs/server/api_utils.py
odcs/server/api_utils.pyc
odcs/server/auth.py
odcs/server/auth.pyc
odcs/server/backend.py
odcs/server/backend.pyc
odcs/server/cache.py
odcs/server/cache.pyc
odcs/server/celery_tasks.py
odcs/server/celery_tasks.pyc
odcs/server/comps.py
odcs/server/comps.pyc
odcs/server/config.py
odcs/server/config.pyc
odcs/server/consumer.pyc
odcs/server/errors.py
odcs/server/errors.pyc
odcs/server/events.py
odcs/server/events.pyc
odcs/server/logger.py
odcs/server/logger.pyc
odcs/server/manage.py
odcs/server/mbs.py
odcs/server/mbs.pyc
odcs/server/mergerepo.py
odcs/server/mergerepo.pyc
odcs/server/messaging.py
odcs/server/messaging.pyc
odcs/server/metrics.py
odcs/server/metrics.pyc
odcs/server/mock_runroot.py
odcs/server/mock_runroot.pyc
odcs/server/models.py
odcs/server/models.pyc
odcs/server/proxy.py
odcs/server/proxy.pyc
odcs/server/pulp.py
odcs-0.2.50.dist-info/LICENSE
odcs-0.2.50.dist-info/METADATA
odcs-0.2.50.dist-info/WHEEL
odcs-0.2.50.dist-info/entry_points.txt
odcs-0.2.50.dist-info/top_level.txt
odcs-0.2.50.dist-info/RECORD
